slackpush/__init__.py
slackpush/__version__.py
slackpush/slackpush.py
slackpush-0.1.1.dist-info/LICENSE
slackpush-0.1.1.dist-info/METADATA
slackpush-0.1.1.dist-info/WHEEL
slackpush-0.1.1.dist-info/top_level.txt
slackpush-0.1.1.dist-info/RECORD
