Metadata-Version: 2.1
Name: slackpush
Version: 0.1.1
Summary: Logging to Slack, made easy.
Home-page: https://github.com/chaiitanyasangani88/SlackPush/
Author: Chaitanya Sangani
Author-email: chaitanyasangani88@gmail.com
License: MIT
Platform: UNKNOWN
Classifier: License :: OSI Approved :: MIT License
Classifier: Programming Language :: Python
Classifier: Programming Language :: Python :: 3
Classifier: Programming Language :: Python :: 3.6
Classifier: Programming Language :: Python :: Implementation :: CPython
Classifier: Programming Language :: Python :: Implementation :: PyPy
Requires-Python: >=3.5.0
Requires-Dist: requests
